llm_commit.py
llm_commit-1.0.3.dist-info/LICENSE
llm_commit-1.0.3.dist-info/METADATA
llm_commit-1.0.3.dist-info/WHEEL
llm_commit-1.0.3.dist-info/entry_points.txt
llm_commit-1.0.3.dist-info/top_level.txt
llm_commit-1.0.3.dist-info/RECORD
