Metadata-Version: 2.2
Name: llm-commit
Version: 1.0.3
Summary: A plugin for llm that generates commit messages
Author-email: Grigoris Ntousakis <greco1996@gmail.com>
License-File: LICENSE
Requires-Dist: click
Requires-Dist: llm
Provides-Extra: test
Requires-Dist: pytest; extra == "test"
